nv_local_gpu_verifier-2.6.4.dist-info/licenses/LICENSE.txt
verifier/__about__.py
verifier/cc_admin.py
verifier/cc_admin_utils.py
verifier/config.py
verifier/verifier.py
verifier/attestation/__init__.py
verifier/attestation/spdm_msrt_req_msg.py
verifier/attestation/spdm_msrt_resp_msg.py
verifier/certs/__init__.py
verifier/certs/verifier_RIM_root.pem
verifier/certs/verifier_device_root.pem
verifier/exceptions/__init__.py
verifier/exceptions/utils.py
verifier/nvml/__init__.py
verifier/nvml/gpu_cert_chains.py
verifier/nvml/nvmlHandlerTest.py
verifier/nvml/test_handle.py
verifier/rim/__init__.py
verifier/rim/golden_measurement.py
verifier/rim/signSchema.xsd
verifier/rim/swidSchema2015.xsd
verifier/rim/xml.xsd
verifier/samples/1010_0200_882_96005E0001_PROD.swidtag
verifier/samples/1010_0200_882_96005E0001_test_no_gpu.swidtag
verifier/samples/1010_0200_882_96005E0003_PROD.swidtag
verifier/samples/1010_0200_882_960074001A_PROD.swidtag
verifier/samples/1010_0200_882_960074001C_PROD.swidtag
verifier/samples/1010_0205_862_96005E0002_PROD.swidtag
verifier/samples/1010_0205_862_96005E0004_PROD.swidtag
verifier/samples/1010_0205_862_960074001F_PROD.swidtag
verifier/samples/1010_0205_862_9600740020_PROD.swidtag
verifier/samples/1010_0210_886_9600740011_PROD.swidtag
verifier/samples/1010_0215_866_9600740010_PROD.swidtag
verifier/samples/Driver_RIM_test_no_gpu.swidtag
verifier/samples/g520_0200_885_9600740001_PROD.swidtag
verifier/samples/g520_0200_885_960074000D_PROD.swidtag
verifier/samples/g520_0202_885_96006D0008_PROD.swidtag
verifier/samples/g520_0202_885_96006D0027_PROD.swidtag
verifier/samples/g520_0202_885_9600740014_PROD.swidtag
verifier/samples/g520_0202_885_9600740018_PROD.swidtag
verifier/samples/g520_0205_865_9600740006_PROD.swidtag
verifier/samples/g520_0205_865_960074000F_PROD.swidtag
verifier/samples/g520_0207_865_9600740015_PROD.swidtag
verifier/samples/g520_0207_865_9600740019_PROD.swidtag
verifier/samples/g520_0213_881_96006D0007_PROD.swidtag
verifier/samples/g520_0213_881_96006D0026_PROD.swidtag
nv_local_gpu_verifier-2.6.4.dist-info/METADATA
nv_local_gpu_verifier-2.6.4.dist-info/WHEEL
nv_local_gpu_verifier-2.6.4.dist-info/top_level.txt
nv_local_gpu_verifier-2.6.4.dist-info/RECORD
