Metadata-Version: 2.4
Name: nv-local-gpu-verifier
Version: 2.6.4
Summary: A Python-based tool that validates GPU measurements by comparing GPU runtime measurements with authenticated golden measurements
Author: NVIDIA
License: BSD-3-Clause
Keywords: confidential-computing,local-gpu-verifier,attestation,NVIDIA,verifier
Classifier: Programming Language :: Python :: 3
Classifier: License :: OSI Approved :: BSD License
Classifier: Operating System :: OS Independent
Requires-Python: >=3.7
License-File: LICENSE.txt
Requires-Dist: cryptography==43.0.1
Requires-Dist: ecdsa==0.18.0
Requires-Dist: lxml>=4.9.1
Requires-Dist: signxml==3.2.0
Requires-Dist: xmlschema==2.2.3
Requires-Dist: pyOpenSSL==24.2.1
Requires-Dist: PyJWT==2.7.0
Requires-Dist: nvidia-ml-py==12.550.52
Requires-Dist: asn1==2.7.0
Dynamic: license-file
